ntils/__init__.py
ntils/useful_func.py
ntils/words_cut.py
ntils_yuxin_wang-0.0.4.dist-info/LICENSE
ntils_yuxin_wang-0.0.4.dist-info/METADATA
ntils_yuxin_wang-0.0.4.dist-info/WHEEL
ntils_yuxin_wang-0.0.4.dist-info/top_level.txt
ntils_yuxin_wang-0.0.4.dist-info/RECORD
