Metadata-Version: 2.1
Name: ntils-yuxin-wang
Version: 0.0.4
Summary: NLP utils
Home-page: https://github.com/pypa/sampleproject
Author: Wang YuXin
Author-email: yuxin.wang@11bee.com
License: UNKNOWN
Platform: UNKNOWN
Classifier: Programming Language :: Python :: 3.6
Classifier: License :: OSI Approved :: MIT License
Classifier: Operating System :: OS Independent
Requires-Dist: Pinyin2Hanzi (==0.1.1)
Requires-Dist: tqdm (==4.31.1)
Requires-Dist: editdistance (==0.5.2)
